meroty_utils/__init__.py
meroty_utils/module.py
meroty_utils-0.1.dist-info/licenses/LICENSE
meroty_utils-0.1.dist-info/METADATA
meroty_utils-0.1.dist-info/WHEEL
meroty_utils-0.1.dist-info/top_level.txt
meroty_utils-0.1.dist-info/RECORD
